setup.py
panoramik_slogging_flask.egg-info/PKG-INFO
panoramik_slogging_flask.egg-info/SOURCES.txt
panoramik_slogging_flask.egg-info/dependency_links.txt
panoramik_slogging_flask.egg-info/requires.txt
panoramik_slogging_flask.egg-info/top_level.txt
panoramik_slogging_flask.egg-info/zip-safe
slogging/__init__.py
slogging/celery.py
slogging/flask.py
slogging/out_handlers/__init__.py
slogging/out_handlers/straight.py
slogging/out_handlers/threading_queue.py
slogging/senders/__init__.py
slogging/senders/debug.py
slogging/senders/fluent.py
slogging/utils/__init__.py
slogging/utils/exception.py